bare_script/__init__.py
bare_script/__main__.py
bare_script/bare.py
bare_script/baredoc.py
bare_script/data.py
bare_script/library.py
bare_script/model.py
bare_script/options.py
bare_script/parser.py
bare_script/runtime.py
bare_script/value.py
bare_script/include/__init__.py
bare_script/include/args.bare
bare_script/include/baredoc.bare
bare_script/include/dataLineChart.bare
bare_script/include/dataTable.bare
bare_script/include/diff.bare
bare_script/include/elementModel.bare
bare_script/include/forms.bare
bare_script/include/markdownUp.bare
bare_script/include/pager.bare
bare_script/include/qrcode.bare
bare_script/include/schemaDoc.bare
bare_script/include/unittest.bare
bare_script/include/unittestMock.bare
bare_script-3.8.17.dist-info/licenses/LICENSE
bare_script-3.8.17.dist-info/METADATA
bare_script-3.8.17.dist-info/WHEEL
bare_script-3.8.17.dist-info/entry_points.txt
bare_script-3.8.17.dist-info/top_level.txt
bare_script-3.8.17.dist-info/RECORD
