Metadata-Version: 2.4
Name: bare-script
Version: 3.8.17
Summary: bare-script
Home-page: https://github.com/craigahobbs/bare-script
Author: Craig A. Hobbs
Author-email: craigahobbs@gmail.com
License: MIT
Keywords: bare-script
Classifier: Development Status :: 5 - Production/Stable
Classifier: Intended Audience :: Developers
Classifier: Operating System :: OS Independent
Classifier: Programming Language :: Python :: 3.10
Classifier: Programming Language :: Python :: 3.11
Classifier: Programming Language :: Python :: 3.12
Classifier: Programming Language :: Python :: 3.13
Classifier: Programming Language :: Python :: 3.14
Classifier: Topic :: Software Development :: Interpreters
Classifier: Topic :: Utilities
License-File: LICENSE
Requires-Dist: schema-markdown>=1.2.0
Requires-Dist: urllib3>=2.5.0
Dynamic: license-file
